emr_sfn_waiter/_jsii/__init__.py
emr_sfn_waiter/_jsii/emr-sfn-waiter@0.0.3.jsii.tgz
emr_sfn_waiter-0.0.3.dist-info/LICENSE
emr_sfn_waiter-0.0.3.dist-info/METADATA
emr_sfn_waiter-0.0.3.dist-info/WHEEL
emr_sfn_waiter-0.0.3.dist-info/top_level.txt
emr_sfn_waiter-0.0.3.dist-info/RECORD
