Metadata-Version: 2.1
Name: emr-sfn-waiter
Version: 0.0.3
Summary: CDK library for an SFN workflow that polls for EMR Serverless job completion
Home-page: https://github.com/alexgelman/emr-sfn-waiter
Author: Alex Gelman<6887237+alexgelman@users.noreply.github.com>
License: MIT
Project-URL: Source, https://github.com/alexgelman/emr-sfn-waiter
Classifier: Intended Audience :: Developers
Classifier: Operating System :: OS Independent
Classifier: Programming Language :: JavaScript
Classifier: Programming Language :: Python :: 3 :: Only
Classifier: Programming Language :: Python :: 3.7
Classifier: Programming Language :: Python :: 3.8
Classifier: Programming Language :: Python :: 3.9
Classifier: Programming Language :: Python :: 3.10
Classifier: Programming Language :: Python :: 3.11
Classifier: Typing :: Typed
Classifier: Development Status :: 5 - Production/Stable
Classifier: License :: OSI Approved
Requires-Python: ~=3.7
License-File: LICENSE
Requires-Dist: aws-cdk-lib (==2.83.1)
Requires-Dist: constructs (<11.0.0,>=10.2.50)
Requires-Dist: jsii (<2.0.0,>=1.83.0)
Requires-Dist: publication (>=0.0.3)
Requires-Dist: typeguard (~=2.13.3)
